ensemblator/__init__.py
ensemblator/ensemblator_cli.py
ensemblator/ensemblator_core.py
ensemblator/generate_exemplar_ensemble.py
ensemblator-4.0.0.dist-info/LICENSE.txt
ensemblator-4.0.0.dist-info/METADATA
ensemblator-4.0.0.dist-info/WHEEL
ensemblator-4.0.0.dist-info/entry_points.txt
ensemblator-4.0.0.dist-info/top_level.txt
ensemblator-4.0.0.dist-info/RECORD
