Metadata-Version: 2.1
Name: ensemblator
Version: 4.0.0
Summary: Ensemblator v3
Home-page: https://github.com/Karplus-Lab-OSU/ensemblator
Author: UNKNOWN
Author-email: UNKNOWN
License: CCA 4.0 IPL
Platform: UNKNOWN
Requires-Dist: biopython
Requires-Dist: matplotlib
Requires-Dist: numpy
Requires-Dist: sklearn
Requires-Dist: scipy
